llama_index/__init__.py
llama_index/readers/__init__.py
llama_index/readers/service_now/__init__.py
llama_index/readers/service_now/base.py
llama_index/readers/service_now/event.py
llama_index_readers_service_now-0.2.2.dist-info/METADATA
llama_index_readers_service_now-0.2.2.dist-info/WHEEL
llama_index_readers_service_now-0.2.2.dist-info/licenses/LICENSE
llama_index_readers_service_now-0.2.2.dist-info/RECORD
