Metadata-Version: 2.4
Name: llama-index-readers-service-now
Version: 0.2.2
Summary: llama-index readers service-now integration
Author-email: Ameetpal Singh <ameetpal.singh@maersk.com>
Maintainer: ameetpal.singh
License-Expression: GPL-3.0-or-later
License-File: LICENSE
Requires-Python: <4.0,>=3.9
Requires-Dist: llama-index-core<0.15,>=0.13.0
Requires-Dist: pysnc<2,>=1.0.0
Requires-Dist: requests<3,>=2.25.0
